distributed_state_network/__init__.py
distributed_state_network/create_key.py
distributed_state_network/dsnode.py
distributed_state_network/handler.py
distributed_state_network/objects/config.py
distributed_state_network/objects/data_packet.py
distributed_state_network/objects/endpoint.py
distributed_state_network/objects/hello_packet.py
distributed_state_network/objects/msg_types.py
distributed_state_network/objects/peers_packet.py
distributed_state_network/objects/signed_packet.py
distributed_state_network/objects/state_packet.py
distributed_state_network/util/__init__.py
distributed_state_network/util/aes.py
distributed_state_network/util/byte_helper.py
distributed_state_network/util/ecdsa.py
distributed_state_network/util/https.py
distributed_state_network/util/key_manager.py
distributed_state_network-0.6.7.dist-info/METADATA
distributed_state_network-0.6.7.dist-info/WHEEL
distributed_state_network-0.6.7.dist-info/licenses/LICENSE
distributed_state_network-0.6.7.dist-info/RECORD
