Metadata-Version: 2.4
Name: distributed-state-network
Version: 0.6.7
Summary: A tool to distribute the state of a network device to other devices on the network
Project-URL: Homepage, https://github.com/erinclemmer/distributed_state_network
Project-URL: Issues, https://github.com/erinclemmer/distributed_state_network/issues
Author-email: Erin Clemmer <erin.c.clemmer@gmail.com>
License-Expression: MIT
License-File: LICENSE
Keywords: distributed,networking
Classifier: Development Status :: 5 - Production/Stable
Classifier: Intended Audience :: Telecommunications Industry
Classifier: License :: OSI Approved :: MIT License
Classifier: Operating System :: OS Independent
Classifier: Programming Language :: Python
Classifier: Topic :: Communications
Classifier: Typing :: Typed
Requires-Python: >=3.10
Requires-Dist: cryptography
Requires-Dist: ecdsa
Requires-Dist: flask
Requires-Dist: ipaddress
Requires-Dist: logging
Requires-Dist: requests
